sleepytimes/VERSION
sleepytimes/__init__.py
sleepytimes/dataset.py
sleepytimes/datatype.py
sleepytimes/graphoelement.py
sleepytimes/sleepytimes.py
sleepytimes/attr/__init__.py
sleepytimes/attr/anat.py
sleepytimes/attr/annotations.py
sleepytimes/attr/chan.py
sleepytimes/detect/__init__.py
sleepytimes/detect/ripple.py
sleepytimes/detect/slowwave.py
sleepytimes/detect/spindle.py
sleepytimes/ioeeg/__init__.py
sleepytimes/ioeeg/blackrock.py
sleepytimes/ioeeg/edf.py
sleepytimes/ioeeg/egimff.py
sleepytimes/ioeeg/fieldtrip.py
sleepytimes/ioeeg/ieeg_org.py
sleepytimes/ioeeg/ktlx.py
sleepytimes/ioeeg/mnefiff.py
sleepytimes/ioeeg/moberg.py
sleepytimes/ioeeg/opbox.py
sleepytimes/ioeeg/phypno.py
sleepytimes/source/__init__.py
sleepytimes/source/linear.py
sleepytimes/source/morph.py
sleepytimes/trans/__init__.py
sleepytimes/trans/filter.py
sleepytimes/trans/frequency.py
sleepytimes/trans/math.py
sleepytimes/trans/merge.py
sleepytimes/trans/montage.py
sleepytimes/trans/peaks.py
sleepytimes/trans/reject.py
sleepytimes/trans/select.py
sleepytimes/utils/__init__.py
sleepytimes/utils/exceptions.py
sleepytimes/utils/simulate.py
sleepytimes/viz/__init__.py
sleepytimes/viz/base.py
sleepytimes/viz/plot_1d.py
sleepytimes/viz/plot_2d.py
sleepytimes/viz/plot_3d.py
sleepytimes/widgets/__init__.py
sleepytimes/widgets/channels.py
sleepytimes/widgets/creation.py
sleepytimes/widgets/info.py
sleepytimes/widgets/notes.py
sleepytimes/widgets/overview.py
sleepytimes/widgets/settings.py
sleepytimes/widgets/spectrum.py
sleepytimes/widgets/traces.py
sleepytimes/widgets/utils.py
sleepytimes/widgets/video.py
sleepytimes/widgets/icons/oxygen/bookmarks-organize.png
sleepytimes/widgets/icons/oxygen/chronometer.png
sleepytimes/widgets/icons/oxygen/configure.png
sleepytimes/widgets/icons/oxygen/document-open.png
sleepytimes/widgets/icons/oxygen/download.png
sleepytimes/widgets/icons/oxygen/edit-table-cell-merge.png
sleepytimes-1.0.2.dist-info/DESCRIPTION.rst
sleepytimes-1.0.2.dist-info/METADATA
sleepytimes-1.0.2.dist-info/RECORD
sleepytimes-1.0.2.dist-info/WHEEL
sleepytimes-1.0.2.dist-info/entry_points.txt
sleepytimes-1.0.2.dist-info/metadata.json
sleepytimes-1.0.2.dist-info/top_level.txt
