Metadata-Version: 2.0
Name: sleepytimes
Version: 1.0.2
Summary: Tools for EEG, ECoG, iEEG, especially for sleep
Home-page: https://github.com/jburn/sleepytimes.git
Author: Jordan O'Byrne
Author-email: jordan.obyrne@gmail.com
License: GPLv3
Keywords: neuroscience analysis sleep EEG ECoG
Platform: UNKNOWN
Classifier: Development Status :: 4 - Beta
Classifier: Environment :: X11 Applications :: Qt
Classifier: Intended Audience :: Healthcare Industry
Classifier: Intended Audience :: Science/Research
Classifier: Topic :: Scientific/Engineering :: Bio-Informatics
Classifier: Topic :: Scientific/Engineering :: Medical Science Apps.
Classifier: Topic :: Scientific/Engineering :: Visualization
Classifier: License :: OSI Approved :: GNU General Public License v3 (GPLv3)
Classifier: Programming Language :: Python :: 3 :: Only
Classifier: Programming Language :: Python :: 3.4
Classifier: Programming Language :: Python :: 3.5
Requires-Dist: numpy
Requires-Dist: scipy
Provides-Extra: all
Requires-Dist: mne; extra == 'all'
Requires-Dist: nibabel; extra == 'all'
Requires-Dist: python-vlc; extra == 'all'
Requires-Dist: request; extra == 'all'
Requires-Dist: scipy; extra == 'all'
Provides-Extra: gui
Requires-Dist: pyqt5; extra == 'gui'
Requires-Dist: scipy; extra == 'gui'
Provides-Extra: viz
Requires-Dist: plotly; extra == 'viz'
Requires-Dist: vispy; extra == 'viz'
